notification_sdk/__init__.py
notification_sdk/notification_sdk.py
notification_sdk/notification_sdk_config.py
notification_sdk/py.typed
ul_notification_sdk_iot_account-3.0.6.dist-info/METADATA
ul_notification_sdk_iot_account-3.0.6.dist-info/WHEEL
ul_notification_sdk_iot_account-3.0.6.dist-info/top_level.txt
ul_notification_sdk_iot_account-3.0.6.dist-info/RECORD
